dlg/__init__.py
dlg/clients.py
dlg/constants.py
dlg/dlg_logging.py
dlg/exceptions.py
dlg/restutils.py
dlg/utils.py
dlg/version_helper.py
dlg/common/__init__.py
dlg/common/deployment_methods.py
dlg/common/k8s_utils.py
dlg/common/network.py
dlg/common/osutils.py
dlg/common/path_utils.py
dlg/common/streams.py
dlg/common/tool.py
dlg/common/version.py
dlg/common/reproducibility/__init__.py
dlg/common/reproducibility/constants.py
dlg/common/reproducibility/reprodata_compare.py
dlg/common/reproducibility/reproducibility.py
dlg/common/reproducibility/reproducibility_fields.py
daliuge_common-6.4.0.dist-info/METADATA
daliuge_common-6.4.0.dist-info/WHEEL
daliuge_common-6.4.0.dist-info/entry_points.txt
daliuge_common-6.4.0.dist-info/top_level.txt
daliuge_common-6.4.0.dist-info/RECORD
