Metadata-Version: 2.4
Name: daliuge-common
Version: 6.4.0
Summary: Data Activated 流 (flow) Graph Engine - Common functionality
Home-page: https://daliuge.icrar.org/
Author: ICRAR DIA Group
Author-email: andreas.wicenec@icrar.org
License: LGPLv2+
Classifier: Development Status :: 5 - Production/Stable
Classifier: Topic :: System :: Distributed Computing
Classifier: Topic :: Scientific/Engineering
Classifier: Intended Audience :: Developers
Classifier: Intended Audience :: Science/Research
Classifier: License :: OSI Approved :: GNU Lesser General Public License v2 (LGPLv2)
Classifier: Operating System :: POSIX :: Linux
Classifier: Operating System :: MacOS
Classifier: Programming Language :: Python :: 3.10
Classifier: Programming Language :: Python :: 3.11
Classifier: Programming Language :: Python :: 3.12
Requires-Dist: GPUtil-fix>=1.4.0
Requires-Dist: np-merklelib
Requires-Dist: pyzmq==25.1.1
Requires-Dist: pydantic>=2.5
Requires-Dist: boto3
Requires-Dist: phonenumbers
Requires-Dist: mailchecker
Requires-Dist: ftfy
Requires-Dist: toml
Requires-Dist: pyyaml
Requires-Dist: beautifulsoup4
Requires-Dist: openpyxl
Requires-Dist: xlrd
Requires-Dist: xmltodict
Requires-Dist: python-benedict[all]
Requires-Dist: pylint
Dynamic: author
Dynamic: author-email
Dynamic: classifier
Dynamic: description
Dynamic: home-page
Dynamic: license
Dynamic: requires-dist
Dynamic: summary
